{"type":"FeatureCollection","features":[{"geometry":{"coordinates":[4.1164463,51.9926093],"crs":{"properties":{"name":"EPSG:4326"},"type":"name"},"type":"Point"},"properties":{"name":"Camping in self-made linen tents, dune grass is used as toilet (1920s)","felt:clipSource":{},"felt:color":"#FF00FF","felt:frame":"none","felt:hasLongDescription":false,"felt:id":"354PX5n6RdC6avCQUSh0DA","felt:locked":false,"felt:ordering":1737395024681388,"felt:radiusDisplayAngle":90,"felt:symbol":"dot","felt:type":"Place","felt:widthScale":1},"type":"Feature"},{"geometry":{"coordinates":[4.1157245,51.9926923],"crs":{"properties":{"name":"EPSG:4326"},"type":"name"},"type":"Point"},"properties":{"name":"A strip with shops is added on the beach (1930s)","felt:clipSource":{},"felt:color":"#FF00FF","felt:frame":"none","felt:hasLongDescription":false,"felt:id":"JJG7WO4aQaO1sV4LjSyVQC","felt:locked":false,"felt:ordering":1737402742447164,"felt:radiusDisplayAngle":90,"felt:symbol":"dot","felt:type":"Place","felt:widthScale":1},"type":"Feature"},{"geometry":{"coordinates":[4.1159023,51.9927707],"crs":{"properties":{"name":"EPSG:4326"},"type":"name"},"type":"Point"},"properties":{"name":"Yearly (de)construction of the shops and wooden camp city (1930s)","felt:clipSource":{},"felt:color":"#FF00FF","felt:frame":"none","felt:hasLongDescription":false,"felt:id":"NlTj2wtwTp2Mm9BwHleb0WC","felt:locked":false,"felt:ordering":1737402745620713,"felt:radiusDisplayAngle":90,"felt:symbol":"dot","felt:type":"Place","felt:widthScale":1},"type":"Feature"}]}