{"type":"FeatureCollection","features":[{"geometry":{"coordinates":[4.1290266,51.9922532],"crs":{"properties":{"name":"EPSG:4326"},"type":"name"},"type":"Point"},"properties":{"name":"Camp 6","felt:clipSource":{},"felt:color":"#FE5E60","felt:id":"vvwkGiswS5iuUkebhX0duA","felt:locked":false,"felt:ordering":1727013167282750,"felt:parentId":"Pe0sOSKFSD9B7E0jw79AEnvC","felt:symbol":"dot","felt:type":"Place"},"type":"Feature"},{"geometry":{"coordinates":[4.1281147,51.993892],"crs":{"properties":{"name":"EPSG:4326"},"type":"name"},"type":"Point"},"properties":{"name":"Camp 1","felt:clipSource":{},"felt:color":"#FE5E60","felt:id":"iPvxRUo6QvKMjT3ajrc1oC","felt:locked":false,"felt:ordering":1727013167282766,"felt:parentId":"Pe0sOSKFSD9B7E0jw79AEnvC","felt:symbol":"dot","felt:type":"Place"},"type":"Feature"},{"geometry":{"coordinates":[4.1254456,51.9904445],"crs":{"properties":{"name":"EPSG:4326"},"type":"name"},"type":"Point"},"properties":{"name":"Old Camp","felt:clipSource":{},"felt:color":"#FE5E60","felt:id":"zd7HQ9C4OTB9BJSBHxzVHNZB","felt:locked":false,"felt:ordering":1727013167282782,"felt:parentId":"Pe0sOSKFSD9B7E0jw79AEnvC","felt:symbol":"dot","felt:type":"Place"},"type":"Feature"},{"geometry":{"coordinates":[4.1289626,51.9934361],"crs":{"properties":{"name":"EPSG:4326"},"type":"name"},"type":"Point"},"properties":{"name":"New Camp","felt:clipSource":{},"felt:color":"#FE5E60","felt:id":"ZW9A9BX3s9BTa9BJBIwiBGmVGA","felt:locked":false,"felt:ordering":1727013167282798,"felt:parentId":"Pe0sOSKFSD9B7E0jw79AEnvC","felt:symbol":"dot","felt:type":"Place"},"type":"Feature"}]}